{
  "__inputs": [
    {
      "name": "DS_PROMETHEUS",
      "label": "Prometheus",
      "description": "",
      "type": "datasource",
      "pluginId": "prometheus",
      "pluginName": "Prometheus"
    }
  ],
  "__requires": [
    { "type": "grafana", "id": "grafana", "name": "Grafana", "version": "10.0.0" },
    { "type": "panel", "id": "timeseries", "name": "Time series", "version": "" },
    { "type": "panel", "id": "stat", "name": "Stat", "version": "" },
    { "type": "datasource", "id": "prometheus", "name": "Prometheus", "version": "1.0.0" }
  ],
  "annotations": { "list": [] },
  "description": "AtomQuest Video Support Platform — Operations Dashboard",
  "editable": true,
  "fiscalYearStartMonth": 0,
  "graphTooltip": 1,
  "id": null,
  "links": [],
  "panels": [
    {
      "datasource": { "type": "prometheus", "uid": "${DS_PROMETHEUS}" },
      "fieldConfig": {
        "defaults": {
          "color": { "mode": "thresholds" },
          "thresholds": {
            "mode": "absolute",
            "steps": [
              { "color": "green", "value": null },
              { "color": "yellow", "value": 5 },
              { "color": "red", "value": 20 }
            ]
          },
          "mappings": [],
          "unit": "short"
        },
        "overrides": []
      },
      "gridPos": { "h": 4, "w": 6, "x": 0, "y": 0 },
      "id": 1,
      "options": { "colorMode": "background", "graphMode": "area", "justifyMode": "auto", "orientation": "auto", "reduceOptions": { "calcs": ["lastNotNull"], "fields": "", "values": false }, "textMode": "auto" },
      "targets": [
        {
          "datasource": { "type": "prometheus", "uid": "${DS_PROMETHEUS}" },
          "expr": "active_sessions_total",
          "legendFormat": "Active sessions",
          "refId": "A"
        }
      ],
      "title": "Active Sessions",
      "type": "stat"
    },
    {
      "datasource": { "type": "prometheus", "uid": "${DS_PROMETHEUS}" },
      "fieldConfig": {
        "defaults": {
          "color": { "mode": "thresholds" },
          "thresholds": {
            "mode": "absolute",
            "steps": [
              { "color": "green", "value": null },
              { "color": "yellow", "value": 10 },
              { "color": "red", "value": 50 }
            ]
          },
          "unit": "short"
        },
        "overrides": []
      },
      "gridPos": { "h": 4, "w": 6, "x": 6, "y": 0 },
      "id": 2,
      "options": { "colorMode": "background", "graphMode": "area", "justifyMode": "auto", "orientation": "auto", "reduceOptions": { "calcs": ["lastNotNull"], "fields": "", "values": false }, "textMode": "auto" },
      "targets": [
        {
          "datasource": { "type": "prometheus", "uid": "${DS_PROMETHEUS}" },
          "expr": "connected_participants_total",
          "legendFormat": "Connected participants",
          "refId": "A"
        }
      ],
      "title": "Connected Participants",
      "type": "stat"
    },
    {
      "datasource": { "type": "prometheus", "uid": "${DS_PROMETHEUS}" },
      "fieldConfig": {
        "defaults": { "color": { "mode": "thresholds" }, "thresholds": { "mode": "absolute", "steps": [{ "color": "blue", "value": null }] }, "unit": "short" },
        "overrides": []
      },
      "gridPos": { "h": 4, "w": 6, "x": 12, "y": 0 },
      "id": 3,
      "options": { "colorMode": "value", "graphMode": "area", "justifyMode": "auto", "orientation": "auto", "reduceOptions": { "calcs": ["lastNotNull"], "fields": "", "values": false }, "textMode": "auto" },
      "targets": [
        {
          "datasource": { "type": "prometheus", "uid": "${DS_PROMETHEUS}" },
          "expr": "sessions_created_total",
          "legendFormat": "Sessions created",
          "refId": "A"
        }
      ],
      "title": "Total Sessions Created",
      "type": "stat"
    },
    {
      "datasource": { "type": "prometheus", "uid": "${DS_PROMETHEUS}" },
      "fieldConfig": {
        "defaults": { "color": { "mode": "thresholds" }, "thresholds": { "mode": "absolute", "steps": [{ "color": "purple", "value": null }] }, "unit": "short" },
        "overrides": []
      },
      "gridPos": { "h": 4, "w": 6, "x": 18, "y": 0 },
      "id": 4,
      "options": { "colorMode": "value", "graphMode": "area", "justifyMode": "auto", "orientation": "auto", "reduceOptions": { "calcs": ["lastNotNull"], "fields": "", "values": false }, "textMode": "auto" },
      "targets": [
        {
          "datasource": { "type": "prometheus", "uid": "${DS_PROMETHEUS}" },
          "expr": "messages_sent_total",
          "legendFormat": "Messages sent",
          "refId": "A"
        }
      ],
      "title": "Total Messages Sent",
      "type": "stat"
    },
    {
      "datasource": { "type": "prometheus", "uid": "${DS_PROMETHEUS}" },
      "fieldConfig": {
        "defaults": { "color": { "mode": "palette-classic" }, "custom": { "axisCenteredZero": false, "axisColorMode": "text", "axisLabel": "", "axisPlacement": "auto", "barAlignment": 0, "drawStyle": "line", "fillOpacity": 15, "gradientMode": "none", "hideFrom": { "legend": false, "tooltip": false, "viz": false }, "lineInterpolation": "smooth", "lineWidth": 2, "pointSize": 5, "scaleDistribution": { "type": "linear" }, "showPoints": "never", "spanNulls": false, "stacking": { "group": "A", "mode": "none" }, "thresholdsStyle": { "mode": "off" } }, "mappings": [], "thresholds": { "mode": "absolute", "steps": [{ "color": "green", "value": null }] }, "unit": "short" },
        "overrides": []
      },
      "gridPos": { "h": 8, "w": 12, "x": 0, "y": 4 },
      "id": 5,
      "options": { "legend": { "calcs": [], "displayMode": "list", "placement": "bottom", "showLegend": true }, "tooltip": { "mode": "multi", "sort": "none" } },
      "targets": [
        {
          "datasource": { "type": "prometheus", "uid": "${DS_PROMETHEUS}" },
          "expr": "active_sessions_total",
          "legendFormat": "Active sessions",
          "refId": "A"
        },
        {
          "datasource": { "type": "prometheus", "uid": "${DS_PROMETHEUS}" },
          "expr": "connected_participants_total",
          "legendFormat": "Connected participants",
          "refId": "B"
        }
      ],
      "title": "Active Sessions & Participants Over Time",
      "type": "timeseries"
    },
    {
      "datasource": { "type": "prometheus", "uid": "${DS_PROMETHEUS}" },
      "fieldConfig": {
        "defaults": { "color": { "mode": "palette-classic" }, "custom": { "axisCenteredZero": false, "axisColorMode": "text", "axisLabel": "", "axisPlacement": "auto", "barAlignment": 0, "drawStyle": "line", "fillOpacity": 10, "gradientMode": "none", "hideFrom": { "legend": false, "tooltip": false, "viz": false }, "lineInterpolation": "smooth", "lineWidth": 2, "pointSize": 5, "scaleDistribution": { "type": "linear" }, "showPoints": "never", "spanNulls": false, "stacking": { "group": "A", "mode": "none" }, "thresholdsStyle": { "mode": "off" } }, "mappings": [], "thresholds": { "mode": "absolute", "steps": [{ "color": "green", "value": null }] }, "unit": "reqps" },
        "overrides": []
      },
      "gridPos": { "h": 8, "w": 12, "x": 12, "y": 4 },
      "id": 6,
      "options": { "legend": { "calcs": [], "displayMode": "list", "placement": "bottom", "showLegend": true }, "tooltip": { "mode": "multi", "sort": "none" } },
      "targets": [
        {
          "datasource": { "type": "prometheus", "uid": "${DS_PROMETHEUS}" },
          "expr": "rate(http_requests_total[5m])",
          "legendFormat": "Request rate",
          "refId": "A"
        },
        {
          "datasource": { "type": "prometheus", "uid": "${DS_PROMETHEUS}" },
          "expr": "rate(http_requests_total{status=~\"5..\"}[5m])",
          "legendFormat": "Error rate (5xx)",
          "refId": "B"
        }
      ],
      "title": "HTTP Request Rate & Error Rate",
      "type": "timeseries"
    },
    {
      "datasource": { "type": "prometheus", "uid": "${DS_PROMETHEUS}" },
      "fieldConfig": {
        "defaults": { "color": { "mode": "palette-classic" }, "custom": { "drawStyle": "line", "fillOpacity": 10, "lineWidth": 2, "showPoints": "never", "spanNulls": false }, "unit": "short" },
        "overrides": []
      },
      "gridPos": { "h": 8, "w": 12, "x": 0, "y": 12 },
      "id": 7,
      "options": { "legend": { "displayMode": "list", "placement": "bottom", "showLegend": true }, "tooltip": { "mode": "multi" } },
      "targets": [
        {
          "datasource": { "type": "prometheus", "uid": "${DS_PROMETHEUS}" },
          "expr": "rate(sessions_created_total[5m])",
          "legendFormat": "Sessions created/s",
          "refId": "A"
        },
        {
          "datasource": { "type": "prometheus", "uid": "${DS_PROMETHEUS}" },
          "expr": "rate(sessions_ended_total[5m])",
          "legendFormat": "Sessions ended/s",
          "refId": "B"
        },
        {
          "datasource": { "type": "prometheus", "uid": "${DS_PROMETHEUS}" },
          "expr": "rate(recordings_started_total[5m])",
          "legendFormat": "Recordings started/s",
          "refId": "C"
        }
      ],
      "title": "Session & Recording Activity",
      "type": "timeseries"
    },
    {
      "datasource": { "type": "prometheus", "uid": "${DS_PROMETHEUS}" },
      "fieldConfig": {
        "defaults": { "color": { "mode": "palette-classic" }, "custom": { "drawStyle": "line", "fillOpacity": 10, "lineWidth": 2, "showPoints": "never" }, "unit": "s" },
        "overrides": []
      },
      "gridPos": { "h": 8, "w": 12, "x": 12, "y": 12 },
      "id": 8,
      "options": { "legend": { "displayMode": "list", "placement": "bottom", "showLegend": true }, "tooltip": { "mode": "multi" } },
      "targets": [
        {
          "datasource": { "type": "prometheus", "uid": "${DS_PROMETHEUS}" },
          "expr": "histogram_quantile(0.50, rate(http_request_duration_seconds_bucket[5m]))",
          "legendFormat": "p50 latency",
          "refId": "A"
        },
        {
          "datasource": { "type": "prometheus", "uid": "${DS_PROMETHEUS}" },
          "expr": "histogram_quantile(0.95, rate(http_request_duration_seconds_bucket[5m]))",
          "legendFormat": "p95 latency",
          "refId": "B"
        },
        {
          "datasource": { "type": "prometheus", "uid": "${DS_PROMETHEUS}" },
          "expr": "histogram_quantile(0.99, rate(http_request_duration_seconds_bucket[5m]))",
          "legendFormat": "p99 latency",
          "refId": "C"
        }
      ],
      "title": "API Response Latency (p50/p95/p99)",
      "type": "timeseries"
    }
  ],
  "refresh": "10s",
  "schemaVersion": 38,
  "tags": ["atomquest", "video", "support"],
  "templating": { "list": [] },
  "time": { "from": "now-1h", "to": "now" },
  "timepicker": {},
  "timezone": "browser",
  "title": "AtomQuest Platform",
  "uid": "atomquest-main",
  "version": 1
}
